pi_display_webthing/__init__.py
pi_display_webthing/app.py
pi_display_webthing/detect_devices.py
pi_display_webthing/display.py
pi_display_webthing/display_webthing.py
pi_display_webthing-0.1.8.dist-info/LICENSE
pi_display_webthing-0.1.8.dist-info/METADATA
pi_display_webthing-0.1.8.dist-info/WHEEL
pi_display_webthing-0.1.8.dist-info/entry_points.txt
pi_display_webthing-0.1.8.dist-info/top_level.txt
pi_display_webthing-0.1.8.dist-info/RECORD
