Metadata-Version: 2.1
Name: pi-display-webthing
Version: 0.1.8
Summary: A web connected LCD display module
Home-page: https://github.com/grro/pi_display_webthing
Author: Gregor Roth
Author-email: gregor.roth@web.de
License: MIT
Keywords: webthing,LCD,display,home automation,raspberry,pi
Platform: UNKNOWN
Classifier: Programming Language :: Python :: 3
Classifier: License :: OSI Approved :: Apache Software License
Classifier: Operating System :: OS Independent
Classifier: Development Status :: 3 - Alpha
Requires-Dist: webthing (>=0.15.0)
Requires-Dist: smbus2
Requires-Dist: RPLCD
